notelbm/__init__.py
notelbm/obs_array.py
notelbm/params.py
notelbm/core/__init__.py
notelbm/core/buff.py
notelbm/core/lattice.py
notelbm/core/shape.py
notelbm/core/speed_nb.py
notelbm/core_bak/__init__.py
notelbm/core_bak/buff.py
notelbm/core_bak/lattice.py
notelbm/core_bak/shape.py
notelbm/example/__init__.py
notelbm/example/example_cavity1.py
notelbm/example/example_cavity3.py
notelbm/example/example_obstacle.py
notelbm/example/example_poiseuille.py
notelbm/example/example_turek.py
notelbm-0.1.11.dist-info/METADATA
notelbm-0.1.11.dist-info/WHEEL
notelbm-0.1.11.dist-info/top_level.txt
notelbm-0.1.11.dist-info/RECORD
