Metadata-Version: 2.1
Name: notelbm
Version: 0.1.11
Summary: notelbm
Home-page: https://github.com/1007530194
Author: niult
Author-email: 1007530194@qq.com
License: UNKNOWN
Platform: UNKNOWN
Requires-Dist: notelbm
